README.md
setup.cfg
setup.py
meansort/__init__.py
meansort.egg-info/PKG-INFO
meansort.egg-info/SOURCES.txt
meansort.egg-info/dependency_links.txt
meansort.egg-info/not-zip-safe
meansort.egg-info/top_level.txt