Metadata-Version: 1.0
Name: meansort
Version: 0.10
Summary: Sorting algorithm by splitting a list by its mean/average.
Home-page: https://github.com/dibsonthis/meansort
Author: Adib Attie
Author-email: adib.attie33@gmail.com
License: MIT
Platform: UNKNOWN
